chikku/__init__.py
chikku/chikku.py
chikku-0.2.dist-info/METADATA
chikku-0.2.dist-info/WHEEL
chikku-0.2.dist-info/entry_points.txt
chikku-0.2.dist-info/top_level.txt
chikku-0.2.dist-info/RECORD
