Metadata-Version: 2.1
Name: chikku
Version: 0.2
Requires-Dist: requests
